<annotation>
	<folder>frames</folder>
	<filename>frame_1531059335.4155877.png</filename>
	<path>C:\Users\Ezra\PythPro\Dasher\datasets\frames\frame_1531059335.4155877.png</path>
	<source>
		<database>Unknown</database>
	</source>
	<size>
		<width>960</width>
		<height>540</height>
		<depth>3</depth>
	</size>
	<segmented>0</segmented>
	<object>
		<name>hanged_man</name>
		<pose>Unspecified</pose>
		<truncated>0</truncated>
		<difficult>0</difficult>
		<bndbox>
			<xmin>435</xmin>
			<ymin>39</ymin>
			<xmax>533</xmax>
			<ymax>127</ymax>
		</bndbox>
	</object>
	<object>
		<name>player</name>
		<pose>Unspecified</pose>
		<truncated>0</truncated>
		<difficult>0</difficult>
		<bndbox>
			<xmin>469</xmin>
			<ymin>281</ymin>
			<xmax>499</xmax>
			<ymax>343</ymax>
		</bndbox>
	</object>
</annotation>
